[
  { "category": "Financial", "title": "Revenue by client (3-year breakdown)", "priority": "P1", "description": "Pull revenue per client for last 36 months; identify concentration and seasonality." },
  { "category": "Financial", "title": "Top-10 client concentration analysis", "priority": "P1", "description": "% of revenue from top-1, top-5, top-10 clients across last 3 years." },
  { "category": "Financial", "title": "Client retention / churn analysis", "priority": "P1", "description": "Annual logo retention, net revenue retention, and churn reasons." },
  { "category": "Financial", "title": "Gross margin by service line", "priority": "P2", "description": "Split revenue & direct cost by service line (bookkeeping, tax, advisory, CAS)." },
  { "category": "Financial", "title": "3-year P&L, Balance Sheet, Cash Flow", "priority": "P1", "description": "Audited or compiled statements, plus monthly trailing 12 for current year." },
  { "category": "Financial", "title": "AR aging + bad-debt history", "priority": "P2", "description": "Current AR aging plus last 3 years of write-offs and collection patterns." },
  { "category": "Financial", "title": "AP aging + payment terms", "priority": "P2", "description": "Open AP, typical terms, any past-due vendor balances." },
  { "category": "Financial", "title": "Debt schedule + covenants", "priority": "P1", "description": "All outstanding debt, rates, terms, covenants, and security." },
  { "category": "Financial", "title": "Working capital peg", "priority": "P1", "description": "Rolling average NWC used to set the deal peg." },
  { "category": "Operations", "title": "Staff roster: roles, tenure, comp", "priority": "P1", "description": "Full employee list with titles, hire dates, base, bonus, equity, benefits." },
  { "category": "Operations", "title": "Compensation structure & benchmarks", "priority": "P2", "description": "Base vs. variable split, commission plans, retention bonuses, severance." },
  { "category": "Operations", "title": "Partner / owner comp & distributions", "priority": "P1", "description": "Owner add-backs, draws, perks to normalize EBITDA." },
  { "category": "Operations", "title": "Key-person dependencies", "priority": "P1", "description": "Identify individuals who hold critical client relationships or IP." },
  { "category": "Operations", "title": "Org chart + reporting lines", "priority": "P2", "description": "Current structure and any planned changes." },
  { "category": "Operations", "title": "Utilization & capacity analysis", "priority": "P2", "description": "Billable-hour utilization, realization %, unbilled WIP." },
  { "category": "Operations", "title": "Service delivery processes / SOPs", "priority": "P2", "description": "Documented workflows, bottlenecks, dependencies." },
  { "category": "Technology", "title": "Tech stack audit", "priority": "P2", "description": "All software, versions, license counts, annual cost, owner, renewal dates." },
  { "category": "Technology", "title": "Data architecture & integrations", "priority": "P2", "description": "Data stores, flow between systems, API surface, custom integrations." },
  { "category": "Technology", "title": "Cybersecurity posture", "priority": "P1", "description": "Controls, MFA coverage, EDR, backups, past incidents." },
  { "category": "Technology", "title": "Client portal / proprietary tooling", "priority": "P2", "description": "In-house apps, ownership, maintenance burden." },
  { "category": "Legal", "title": "Pending / threatened litigation", "priority": "P1", "description": "All open matters, reserves, plus prior claims history." },
  { "category": "Legal", "title": "Professional liability / E&O coverage", "priority": "P1", "description": "Policy limits, deductibles, claims history, tail options." },
  { "category": "Legal", "title": "Employment disputes & settlements", "priority": "P2", "description": "Claims, PIPs, separation agreements, restrictive covenants enforced." },
  { "category": "Legal", "title": "Regulatory / PCAOB / state-board matters", "priority": "P1", "description": "Any open inquiries, consent orders, peer review findings." },
  { "category": "Legal", "title": "IP ownership & work-for-hire", "priority": "P2", "description": "Assignments signed by every employee; IP created outside employment." },
  { "category": "Legal", "title": "NDAs, non-competes, non-solicits", "priority": "P2", "description": "Coverage of key employees, enforceability by state." },
  { "category": "Commercial", "title": "Client contract review (top 20)", "priority": "P1", "description": "Term, auto-renew, change-of-control, SLAs, fee schedule, termination." },
  { "category": "Commercial", "title": "Change-of-control consents required", "priority": "P1", "description": "Flag clients and vendors requiring consent for transaction." },
  { "category": "Commercial", "title": "Pricing & proposal process", "priority": "P2", "description": "Standard rates, discounting authority, quote-to-close metrics." },
  { "category": "Commercial", "title": "Pipeline & sales forecast", "priority": "P2", "description": "Active opportunities, weighted pipeline, win rates, cycle times." },
  { "category": "Real Estate", "title": "Lease obligations & terms", "priority": "P1", "description": "All leases, square footage, rent, escalators, renewal options, exit costs." },
  { "category": "Real Estate", "title": "Remote / hybrid policy", "priority": "P2", "description": "Current in-office requirement and any upcoming changes." },
  { "category": "HR", "title": "Benefits obligations (health, 401k, PTO)", "priority": "P1", "description": "Plan documents, employer match, accrued PTO liability." },
  { "category": "HR", "title": "Employee handbook & policies", "priority": "P2", "description": "Current version, last legal review, state-specific addenda." },
  { "category": "HR", "title": "Payroll tax compliance", "priority": "P1", "description": "941 filings, state SUI/SIT, 1099 vs. W-2 classification review." },
  { "category": "Tax", "title": "Federal & state tax filings (3 years)", "priority": "P1", "description": "All returns, extensions, open audits, carryforwards." },
  { "category": "Tax", "title": "Sales / use / franchise tax nexus review", "priority": "P2", "description": "States where nexus established, compliance status, exposure." },
  { "category": "Integration", "title": "Day-1 / Day-30 / Day-100 plan", "priority": "P2", "description": "Who owns what, retention bonuses, client communication plan." },
  { "category": "Integration", "title": "Synergy model (cost + revenue)", "priority": "P2", "description": "Quantified synergies with owners and timing." },
  { "category": "Integration", "title": "Cultural fit / values alignment", "priority": "P2", "description": "Leadership interviews, values survey, red flags." }
]
